refinire_rag_chroma/__init__.py
refinire_rag_chroma/chroma_vector_store.py
refinire_rag_chroma/config.py
refinire_rag_chroma-0.0.6.dist-info/METADATA
refinire_rag_chroma-0.0.6.dist-info/WHEEL
refinire_rag_chroma-0.0.6.dist-info/entry_points.txt
refinire_rag_chroma-0.0.6.dist-info/top_level.txt
refinire_rag_chroma-0.0.6.dist-info/RECORD
