Metadata-Version: 2.4
Name: refinire-rag-chroma
Version: 0.0.6
Summary: ChromaDB VectorStore plugin for refinire-rag
Author-email: refinire-rag-chroma contributors <noreply@example.com>
License: MIT
Project-URL: Homepage, https://github.com/kitfactory/refinire_rag_chroma
Project-URL: Repository, https://github.com/kitfactory/refinire_rag_chroma
Project-URL: Issues, https://github.com/kitfactory/refinire_rag_chroma/issues
Keywords: refinire-rag,chromadb,vector-store,plugin
Classifier: Development Status :: 4 - Beta
Classifier: Intended Audience :: Developers
Classifier: License :: OSI Approved :: MIT License
Classifier: Programming Language :: Python :: 3
Classifier: Programming Language :: Python :: 3.10
Classifier: Programming Language :: Python :: 3.11
Classifier: Programming Language :: Python :: 3.12
Classifier: Topic :: Software Development :: Libraries :: Python Modules
Classifier: Topic :: Scientific/Engineering :: Artificial Intelligence
Requires-Python: >=3.10
Requires-Dist: chromadb>=0.4.0
Requires-Dist: numpy>=2.2.6
Requires-Dist: oneenv>=0.3.1
Requires-Dist: pydantic>=2.0.0
Requires-Dist: refinire-rag>=0.1.5
Provides-Extra: dev
Requires-Dist: pytest>=8.0.0; extra == "dev"
Requires-Dist: pytest-cov>=4.1.0; extra == "dev"
